qunomon_lite/__init__.py
qunomon_lite/__version__.py
qunomon_lite/ait.py
qunomon_lite/ait_core.py
qunomon_lite/cli.py
qunomon_lite/print_helper.py
qunomon_lite-0.1.2.dist-info/LICENSE
qunomon_lite-0.1.2.dist-info/METADATA
qunomon_lite-0.1.2.dist-info/WHEEL
qunomon_lite-0.1.2.dist-info/entry_points.txt
qunomon_lite-0.1.2.dist-info/top_level.txt
qunomon_lite-0.1.2.dist-info/RECORD
