Metadata-Version: 2.1
Name: qunomon-lite
Version: 0.1.2
Summary: Lightweight tool for using Qunomon, AIT
Home-page: https://github.com/ads-ad-itcenter/qunomon-lite
Author: Masanori Hayashi
Author-email: hayashi.masanori@adniss.jp
License: Apache License 2.0
Platform: UNKNOWN
Requires-Python: >=3.6
License-File: LICENSE
Requires-Dist: docker
Requires-Dist: rich[jupyter]
